README
setup.py
c2c/__init__.py
c2c.recipe.msgfmt.egg-info/PKG-INFO
c2c.recipe.msgfmt.egg-info/SOURCES.txt
c2c.recipe.msgfmt.egg-info/dependency_links.txt
c2c.recipe.msgfmt.egg-info/entry_points.txt
c2c.recipe.msgfmt.egg-info/namespace_packages.txt
c2c.recipe.msgfmt.egg-info/not-zip-safe
c2c.recipe.msgfmt.egg-info/requires.txt
c2c.recipe.msgfmt.egg-info/top_level.txt
c2c/recipe/__init__.py
c2c/recipe/msgfmt/__init__.py
c2c/recipe/msgfmt/buildout.py