Metadata-Version: 1.1
Name: c2c.recipe.msgfmt
Version: 0.2.2
Summary: A buildout recipe to compile message catalog to binary format.
Home-page: https://github.com/camptocamp/c2c.recipe.msgfmt
Author: Frederic Junod
Author-email: frederic.junod@camptocamp.com
License: MIT License
Platform: UNKNOWN
Classifier: Framework :: Buildout
Classifier: Intended Audience :: Developers
Classifier: Topic :: Software Development :: Build Tools
Classifier: Topic :: Software Development :: Libraries :: Python Modules
Classifier: License :: OSI Approved :: MIT License
